[
    {
        "name": "Sun",
        "color": "#ffdd55",
        "baseMass": 1.0,
        "orbit": null,
        "radiusDraw": 25
    },
    {
        "name": "Mercury",
        "color": "#b5b5b5",
        "baseMass": 1.651e-7,
        "orbit": {
            "semiMajorAxis": 0.38709927,
            "eccentricity": 0.20563593,
            "longitudeOfPerihelion": 77.45779628,
            "meanLongitude": 252.25032350
        },
        "radiusDraw": 6
    },
    {
        "name": "Venus",
        "color": "#e1c699",
        "baseMass": 2.447e-6,
        "orbit": {
            "semiMajorAxis": 0.72333566,
            "eccentricity": 0.00677672,
            "longitudeOfPerihelion": 131.60246718,
            "meanLongitude": 181.97909950
        },
        "radiusDraw": 9
    },
    {
        "name": "Earth",
        "color": "#4ea1ff",
        "baseMass": 3.003489e-6,
        "orbit": {
            "semiMajorAxis": 1.00000261,
            "eccentricity": 0.01671123,
            "longitudeOfPerihelion": 102.93768193,
            "meanLongitude": 100.46457166
        },
        "radiusDraw": 10
    },
    {
        "name": "Mars",
        "color": "#ff6f4e",
        "baseMass": 3.227e-7,
        "orbit": {
            "semiMajorAxis": 1.52371034,
            "eccentricity": 0.09339410,
            "longitudeOfPerihelion": -23.94362959,
            "meanLongitude": -4.55343205
        },
        "radiusDraw": 7
    },
    {
        "name": "Jupiter",
        "color": "#ffb347",
        "baseMass": 9.5458e-4,
        "orbit": {
            "semiMajorAxis": 5.20288700,
            "eccentricity": 0.04838624,
            "longitudeOfPerihelion": 14.72847983,
            "meanLongitude": 34.39644051
        },
        "radiusDraw": 20
    },
    {
        "name": "Saturn",
        "color": "#ffd27f",
        "baseMass": 2.858e-4,
        "orbit": {
            "semiMajorAxis": 9.53667594,
            "eccentricity": 0.05386179,
            "longitudeOfPerihelion": 92.59887831,
            "meanLongitude": 49.95424423
        },
        "radiusDraw": 18
    },
    {
        "name": "Uranus",
        "color": "#9bd3ff",
        "baseMass": 4.366e-5,
        "orbit": {
            "semiMajorAxis": 19.18916464,
            "eccentricity": 0.04725744,
            "longitudeOfPerihelion": 170.95427630,
            "meanLongitude": 313.23810451
        },
        "radiusDraw": 14
    },
    {
        "name": "Neptune",
        "color": "#5aa0ff",
        "baseMass": 5.149e-5,
        "orbit": {
            "semiMajorAxis": 30.06992276,
            "eccentricity": 0.00859048,
            "longitudeOfPerihelion": 44.96476227,
            "meanLongitude": -55.12002969
        },
        "radiusDraw": 14
    }
]